poemar/__init__.py
poemar-0.0.4.dist-info/licenses/LICENSE
poemar-0.0.4.dist-info/METADATA
poemar-0.0.4.dist-info/WHEEL
poemar-0.0.4.dist-info/top_level.txt
poemar-0.0.4.dist-info/RECORD
