Metadata-Version: 2.4
Name: poemar
Version: 0.0.4
Summary: library for writing poems
Home-page: https://github.com/montoyamoraga/poemarpy
Author: montoyamoraga
Author-email: montoyamoraga@gmail.com
License: MIT
Classifier: Programming Language :: Python :: 3
Classifier: Development Status :: 3 - Alpha
License-File: LICENSE
Dynamic: author
Dynamic: author-email
Dynamic: classifier
Dynamic: description
Dynamic: description-content-type
Dynamic: home-page
Dynamic: license
Dynamic: license-file
Dynamic: summary
